{
    "WhiteSidePlayerName": "Luizz",
    "BlackSidePlayerName": "jules",
    "AageGameTypeKey": 16,
    "AageGameTypeName": "Copenhagen Hnefatafl 11x11",
    "WhoMovedFirst": "black",
    "BlackPiecesCaptured": 2,
    "WhitePiecesCaptured": 3,
    "Moves": [
        "a5-b5",
        "h6-h9",
        "f10-i10",
        "g7-j7",
        "i10-i7xj7",
        "f8-i8",
        "h11-i11",
        "g6-i6xi7",
        "h1-i1",
        "f7-j7",
        "f11-f10",
        "g5-j5xj6",
        "k8-k9",
        "j7-j11",
        "g11-h11",
        "f6-f9",
        "b6-b9",
        "j5-j2",
        "k4-k2",
        "h9-h1",
        "f2-i2xj2",
        "f9-j9",
        "k7-j7",
        "j11-j10",
        "f10-i10",
        "h1-h10xi10",
        "i11-i10",
        "j10-k10",
        "resigned"
    ],
    "WhoWon": "White"
}