{
    "WhiteSidePlayerName": "Luizz",
    "BlackSidePlayerName": "kAAgEE",
    "AageGameTypeKey": 16,
    "AageGameTypeName": "Copenhagen Hnefatafl 11x11",
    "WhoMovedFirst": "black",
    "BlackPiecesCaptured": 3,
    "WhitePiecesCaptured": 2,
    "Moves": [
        "g11-g9",
        "h6-h9",
        "f10-f9",
        "e7-e10",
        "f11-f10",
        "e10-b10",
        "b6-b9",
        "f8-b8xb9",
        "f9-b9",
        "e5-e2",
        "a7-b7xb8",
        "g5-g2xf2",
        "d11-b11xb10",
        "g7-j7",
        "j6-i6",
        "j7-j2",
        "i6-i9xh9",
        "g6-i6",
        "f1-f2",
        "i6-i1",
        "k4-j4",
        "f6-h6",
        "k5-k2",
        "h6-h3",
        "resigned"
    ],
    "WhoWon": "White"
}