{
    "WhiteSidePlayerName": "Cantlose",
    "BlackSidePlayerName": "herjan",
    "AageGameTypeKey": 16,
    "AageGameTypeName": "Copenhagen Hnefatafl 11x11",
    "WhoMovedFirst": "black",
    "BlackPiecesCaptured": 8,
    "WhitePiecesCaptured": 1,
    "Moves": [
        "g11-g10",
        "f4-c4",
        "f2-c2",
        "f5-f2",
        "h1-h3",
        "g5-j5",
        "k4-j4xj5",
        "d6-d9",
        "g1-g2",
        "h6-h8",
        "j6-j9",
        "f8-b8",
        "g10-i10",
        "e5-d5",
        "b6-b3",
        "d9-d10",
        "j9-d9xd10",
        "f7-f9",
        "f10-c10",
        "b8-b9",
        "c10-c9",
        "b9-b10",
        "d11-b11",
        "f9-j9",
        "k8-k9",
        "f6-f10",
        "a8-a10",
        "f10-c10",
        "e11-c11",
        "h8-c8xc9",
        "b3-b9xb10",
        "c8-i8",
        "d9-i9xj9",
        "e6-b6",
        "a4-b4",
        "g6-j6",
        "k7-i7xi8",
        "d5-i5",
        "e1-e2xf2",
        "i5-i1",
        "i7-i6xj6",
        "c10-c8",
        "i9-j9",
        "g7-k7",
        "k9-k8xk7",
        "c8-g8",
        "k5-g5",
        "resigned"
    ],
    "WhoWon": "Black"
}