{
    "WhiteSidePlayerName": "Docbullen",
    "BlackSidePlayerName": "Hagbard",
    "AageGameTypeKey": 163,
    "AageGameTypeName": "Dald&oslash;s 3x16",
    "WhoMovedFirst": "black",
    "BlackPiecesCaptured": 0,
    "WhitePiecesCaptured": 0,
    "Moves": [
        "c1-b3",
        "a1-b1",
        "b3-b10",
        "b1-b6",
        "c2-c1",
        "b6-b11",
        "b13-a16xa16",
        "b11-b16",
        "c3-c2",
        "b16-c14xc14",
        "c1-b4",
        "c14-c10xc10",
        "a13-a11xa11",
        "a2-a1",
        "b6-b10",
        "c6-c2xc2",
        "c3-b2xb2",
        "c2-b2xb2",
        "b13-b17",
        "b2-b8",
        "c5-b1",
        "b8-b14",
        "b17-a14xa14",
        "b14-c16xc16",
        "a14-a10xa10",
        "a4-a3xa3",
        "c7-c6",
        "a3-b6",
        "c6-c4",
        "c13-c9xc9",
        "a10-a6xa6",
        "b10-c16",
        "c11-c9xc9",
        "c16-c11xc11",
        "b7-b9",
        "c11-c9xc9",
        "c15-c11",
        "c9-c5",
        "c7-c5xc5",
        "a9-a8",
        "b1-b7",
        "a4-b5",
        "b13-a15xa15",
        "a12-a11",
        "a15-a12",
        "a8-a4",
        "c11-c4",
        "a11-a6",
        "a12-a4xa4"
    ],
    "WhoWon": "Black"
}