{
    "WhiteSidePlayerName": "p59xy",
    "BlackSidePlayerName": "kAAgEE",
    "AageGameTypeKey": 16,
    "AageGameTypeName": "Copenhagen Hnefatafl 11x11",
    "WhoMovedFirst": "black",
    "BlackPiecesCaptured": 2,
    "WhitePiecesCaptured": 3,
    "Moves": [
        "d1-d3",
        "f4-i4",
        "k4-j4",
        "g5-j5",
        "k7-i7",
        "h6-h3",
        "f2-j2",
        "h3-j3xj4",
        "k5-k3",
        "f5-f3",
        "h1-i1",
        "f8-j8",
        "i7-i8xj8",
        "g7-j7xj6",
        "k8-k7",
        "j7-j9",
        "f10-j10",
        "j9-b9",
        "d11-d10",
        "f7-f10",
        "d10-b10",
        "f6-f9",
        "h11-h9",
        "d6-d11",
        "b10-c10",
        "f9-c9",
        "c10-c11xd11",
        "c9-c10",
        "a8-a10",
        "b9-a9xa10",
        "resigned"
    ],
    "WhoWon": "White"
}