{
    "WhiteSidePlayerName": "frenir",
    "BlackSidePlayerName": "SebastianMucke",
    "AageGameTypeKey": 16,
    "AageGameTypeName": "Copenhagen Hnefatafl 11x11",
    "WhoMovedFirst": "black",
    "BlackPiecesCaptured": 2,
    "WhitePiecesCaptured": 3,
    "Moves": [
        "a8-c8",
        "h6-h3",
        "d1-d3",
        "f4-c4",
        "k4-i4",
        "g5-j5",
        "i4-i5xj5",
        "e5-e2",
        "b6-b2",
        "g6-g2xf2",
        "h1-h2",
        "f6-i6",
        "h11-h4xh3",
        "i6-i11",
        "j6-j11",
        "i11-i9",
        "j11-j9",
        "i9-a9",
        "f10-a10",
        "a9-c9",
        "a10-c10",
        "e7-c7xc8",
        "a7-a9",
        "c9-b9",
        "d11-b11",
        "b9-b10",
        "a9-a10",
        "d6-d10xc10",
        "e11-c11",
        "d10-d9",
        "resigned"
    ],
    "WhoWon": "White"
}