{
    "WhiteSidePlayerName": "Hagbard",
    "BlackSidePlayerName": "sea slug",
    "AageGameTypeKey": 10,
    "AageGameTypeName": "Skalk Hnefatafl 9x9 (ExpoMedia)",
    "WhoMovedFirst": "black",
    "BlackPiecesCaptured": 0,
    "WhitePiecesCaptured": 0,
    "Moves": [
        "e8c8",
        "e4b4",
        "b5b7",
        "g5g4",
        "h5h3",
        "f5f2",
        "e2c2",
        "d5d2",
        "e1e2",
        "e6d6",
        "d1d2",
        "e5g5",
        "c8g8",
        "g4g1",
        "i5h5",
        "g5g2",
        "i4i2",
        "b4i4",
        "h3i3",
        "e3h3",
        "f9f3",
        "d6g6",
        "i6i5",
        "g6g3",
        "a4h4",
        "e7e3",
        "i2h2",
        "g1h1",
        "e2f2"
    ],
    "WhoWon": "Black"
}