{
    "WhiteSidePlayerName": "Oddur",
    "BlackSidePlayerName": "Hagbard",
    "AageGameTypeKey": 3,
    "AageGameTypeName": "Berserk Hnefatafl 11x11",
    "WhoMovedFirst": "black",
    "BlackPiecesCaptured": 5,
    "WhitePiecesCaptured": 1,
    "Moves": [
        "d11d9",
        "g7g9",
        "f10j10",
        "f7i7",
        "f2i2",
        "e5e4",
        "a8c8",
        "f5c5",
        "b6b2",
        "e4b4",
        "a7b7",
        "f4j4",
        "i2i4",
        "f6f3",
        "c4c3",
        "e7e10",
        "d9d10",
        "f8f10",
        "k8f8",
        "g9b9",
        "d10b10",
        "b9a9",
        "k7k9",
        "e10c10",
        "e11c11",
        "a9a10",
        "f8f9",
        "f3k3",
        "b2k2",
        "k3j3",
        "k2i2",
        "j3k3"
    ],
    "WhoWon": "Draw"
}