{
    "WhiteSidePlayerName": "Casshern",
    "BlackSidePlayerName": "Harry64",
    "AageGameTypeKey": 33,
    "AageGameTypeName": "Historical Hnefatafl 13x13",
    "WhoMovedFirst": "black",
    "BlackPiecesCaptured": 5,
    "WhitePiecesCaptured": 6,
    "Moves": [
        "i13-i10",
        "h6-h3",
        "i1-i3xh3",
        "h7-h3",
        "m9-j9",
        "j7-j3xi3",
        "k7-i7",
        "f6-f3xg3",
        "l8-i8xi9",
        "g4-g2",
        "j9-g9xg10",
        "i5-i2xh2",
        "h12-h9",
        "j3-j8xi8",
        "i7-h7xh8",
        "i2-i7xh7",
        "h1-h2xg2",
        "i7-i2",
        "m7-i7",
        "g6-i6",
        "g1-g4",
        "g7-h7",
        "b6-h6",
        "j8-i8xi7",
        "h9-h8",
        "h7-m7"
    ],
    "WhoWon": "White"
}