{
    "WhiteSidePlayerName": "Holidayinnes",
    "BlackSidePlayerName": "Bogd khan",
    "AageGameTypeKey": 3,
    "AageGameTypeName": "Berserk Hnefatafl 11x11",
    "WhoMovedFirst": "black",
    "BlackPiecesCaptured": 7,
    "WhitePiecesCaptured": 5,
    "Moves": [
        "d11-d9",
        "h6-h9",
        "k7-j7",
        "f4-i4",
        "f2-i2",
        "d6-d3",
        "d1-d2",
        "f5-f2",
        "h1-h3",
        "g5-g3",
        "b6-b3",
        "e6-b6",
        "a8-c8",
        "e7-c7",
        "d9-c9",
        "f6-d6",
        "f10-d10",
        "d6-d9",
        "j6-h6xg6",
        "h9-k9",
        "h11-h9",
        "d9-g9",
        "k6-i6",
        "f8-i8",
        "d10-i10",
        "i8-i9xh9",
        "c8-i8xi9",
        "g9-j9",
        "i10-j10",
        "j9-i9",
        "j10-i10",
        "e5-i5",
        "b3-b10",
        "i9-j9",
        "i10-j10",
        "g7-i7xi6",
        "a4-d4xd3",
        "i7-i11",
        "c6-c8",
        "i5-i8",
        "c8-h8",
        "i11-j11xj10",
        "b10-j10",
        "j9-g9",
        "g11-i11xj11",
        "g9-g8xh8",
        "e1-e8",
        "g8-g10",
        "f3-f10",
        "g10-i10",
        "c9-i9",
        "k9-k10xj10",
        "j7-j10",
        "i10-g10",
        "k8-k9xk10",
        "g10-g3",
        "f1-f3",
        "i8-g8",
        "h3-i3",
        "g3-g5",
        "a5-e5",
        "i4-i7",
        "a7-e7",
        "resigned"
    ],
    "WhoWon": "Black"
}