{
    "WhiteSidePlayerName": "Ded fomich",
    "BlackSidePlayerName": "Casshern",
    "AageGameTypeKey": 7,
    "AageGameTypeName": "Historical Hnefatafl 9x9 (Saami Tablut)",
    "WhoMovedFirst": "black",
    "BlackPiecesCaptured": 5,
    "WhitePiecesCaptured": 2,
    "Moves": [
        "e2-c2",
        "e4-f4",
        "e8-g8",
        "f5-f6",
        "b5-b7",
        "e3-h3",
        "d1-d3",
        "g5-g1",
        "i4-h4",
        "e5-g5",
        "c2-h2xh3",
        "e6-e3",
        "f1-f3xe3",
        "e7-e3",
        "f3-g3",
        "c5-c3xd3",
        "a5-c5xd5",
        "g5-d5",
        "h2-d2",
        "c3-c2",
        "d9-d6",
        "f4-d4",
        "b7-b2xc2",
        "e3-e7",
        "d6-d7",
        "f6-c6",
        "f9-f7xe7",
        "d4-c4xc5",
        "b2-b5",
        "c4-c1",
        "h4-c4",
        "d5-f5",
        "g3-f3",
        "f5-e5",
        "i5-i4",
        "g1-g3",
        "i4-e4",
        "e5-d5",
        "g8-g5",
        "d5-d3",
        "e4-d4"
    ],
    "WhoWon": "Black"
}