{
    "WhiteSidePlayerName": "Epoc",
    "BlackSidePlayerName": "tonythebook",
    "AageGameTypeKey": 16,
    "AageGameTypeName": "Copenhagen Hnefatafl 11x11",
    "WhoMovedFirst": "black",
    "BlackPiecesCaptured": 3,
    "WhitePiecesCaptured": 1,
    "Moves": [
        "h1-h3",
        "f4-i4",
        "k4-j4",
        "g7-g10",
        "h11-h10xg10",
        "g6-g10",
        "h10-i10",
        "e7-e10xf10",
        "d11-d10",
        "h6-h9",
        "j6-j9",
        "h9-h11",
        "j9-g9xg10",
        "f6-j6",
        "k8-j8",
        "i4-i9",
        "i10-i11xh11",
        "e10-j10",
        "d10-i10",
        "i9-k9",
        "i10-i7",
        "j6-i6",
        "i7-i10",
        "i6-i1",
        "j4-j1",
        "i1-i9",
        "a4-i4",
        "k9-k8",
        "resigned"
    ],
    "WhoWon": "White"
}