{
    "WhiteSidePlayerName": "Dimetr",
    "BlackSidePlayerName": "Alex Hnefatafl",
    "AageGameTypeKey": 7,
    "AageGameTypeName": "Historical Hnefatafl 9x9 (Saami Tablut)",
    "WhoMovedFirst": "black",
    "BlackPiecesCaptured": 6,
    "WhitePiecesCaptured": 1,
    "Moves": [
        "e2-c2",
        "e4-f4",
        "e8-g8",
        "f5-f6",
        "b5-b7",
        "e3-h3",
        "d1-d3",
        "g5-g1",
        "i4-h4",
        "h3-h2",
        "i5-i1",
        "e5-g5",
        "a4-c4",
        "e6-e3",
        "f1-f3xe3",
        "h2-f2xf3",
        "d3-g3",
        "f2-f1",
        "c2-d2",
        "g5-e5",
        "a6-c6xc5",
        "d5-c5",
        "d9-d5",
        "e5-e3",
        "d5-d3",
        "e3-e6",
        "b7-d7",
        "e7-h7",
        "a5-b5",
        "f6-f8",
        "e9-e8xf8",
        "f4-f8",
        "d7-f7xf8",
        "f1-f2",
        "d3-d5xc5",
        "f2-f4",
        "c4-e4",
        "f4-f6",
        "c6-d6",
        "f6-g6",
        "f7-f6",
        "e6-e5",
        "i6-h6xg6",
        "resigned"
    ],
    "WhoWon": "Black"
}