{
    "WhiteSidePlayerName": "MochaBoi",
    "BlackSidePlayerName": "bluepot9",
    "AageGameTypeKey": 33,
    "AageGameTypeName": "Historical Hnefatafl 13x13",
    "WhoMovedFirst": "black",
    "BlackPiecesCaptured": 4,
    "WhitePiecesCaptured": 2,
    "Moves": [
        "m9-j9",
        "h8-h9",
        "m5-j5",
        "h6-h5",
        "i1-i4",
        "g6-i6",
        "a9-d9",
        "h5-h4",
        "e1-e4",
        "f6-f4",
        "b6-e6xe5",
        "d7-d4xe4",
        "b8-b4",
        "g7-g5",
        "f2-e2",
        "f7-e7",
        "e13-e10",
        "g5-c5",
        "b4-c4",
        "c5-d5",
        "a8-e8xe9xe7",
        "f8-f9",
        "f1-d1",
        "f9-g9",
        "e2-e5",
        "f4-f5xe5",
        "e6-e4xd4",
        "d5-d4",
        "g3-d3",
        "d4-d6",
        "a6-c6",
        "i6-e6",
        "a5-d5",
        "d6-d7",
        "e8-e7"
    ],
    "WhoWon": "Black"
}