{
    "WhiteSidePlayerName": "Pi&eacute;96",
    "BlackSidePlayerName": "jrton80",
    "AageGameTypeKey": 4,
    "AageGameTypeName": "Fetlar Hnefatafl 11x11",
    "WhoMovedFirst": "black",
    "BlackPiecesCaptured": 7,
    "WhitePiecesCaptured": 4,
    "Moves": [
        "e1-e3",
        "g7-j7",
        "k5-i5",
        "h6-h9",
        "k8-j8xj7",
        "f7-j7",
        "i5-i7xj7",
        "f4-i4",
        "k4-j4",
        "f8-c8",
        "i7-i9",
        "h9-b9",
        "a8-a9",
        "f6-f9",
        "d11-d9",
        "f9-e9",
        "f10-c10",
        "c8-c9xd9",
        "j8-c8xc9",
        "d6-d11",
        "c8-c9xb9",
        "f5-f8",
        "b6-b10",
        "f8-j8",
        "h11-h9",
        "i4-i7",
        "k7-j7",
        "e9-e10",
        "g11-g10",
        "e10-f10",
        "j6-h6xg6",
        "f10-f3",
        "h6-h3",
        "d11-d3xe3",
        "b10-b3",
        "e6-j6xj7",
        "i9-i8",
        "g5-k5",
        "a6-i6xi7xj6",
        "e7-k7xk6",
        "g1-g3",
        "f3-f7",
        "h3-h7",
        "resigned"
    ],
    "WhoWon": "Black"
}