{
    "WhiteSidePlayerName": "Draganov",
    "BlackSidePlayerName": "jilles",
    "AageGameTypeKey": 31,
    "AageGameTypeName": "Simple Tafl 11x11",
    "WhoMovedFirst": "black",
    "BlackPiecesCaptured": 2,
    "WhitePiecesCaptured": 1,
    "Moves": [
        "e1-c1",
        "f3-e3",
        "k5-k3",
        "e6-e9",
        "a7-a9",
        "d6-d1",
        "b7-d7",
        "c6-c7",
        "b6-b7xc7",
        "f6-c6",
        "a9-c9",
        "f4-b4",
        "c1-c3",
        "d1-d3",
        "a6-b6",
        "c6-e6",
        "c3-a3",
        "f8-a8",
        "k7-k8",
        "e6-e4",
        "k6-k4",
        "b4-b1",
        "b5-b4",
        "b1-e1xe2",
        "c9-c1",
        "e4-h4",
        "k3-h3",
        "h4-i4",
        "g2-i2",
        "i4-e4",
        "e11-c11",
        "d3-c3",
        "c1-d1xe1",
        "e4-e8",
        "c11-c8",
        "e3-g3",
        "b4-e4",
        "e8-h8",
        "g10-h10",
        "i6-i11",
        "k8-i8",
        "h6-h7",
        "g11-g8"
    ],
    "WhoWon": "Black"
}