{
    "WhiteSidePlayerName": "Alex Hnefatafl",
    "BlackSidePlayerName": "L716",
    "AageGameTypeKey": 129,
    "AageGameTypeName": "Historical Hnefatafl 7x7 (Irish Brandubh 2)",
    "WhoMovedFirst": "black",
    "BlackPiecesCaptured": 2,
    "WhitePiecesCaptured": 3,
    "Moves": [
        "f4-f5",
        "e4-f4",
        "d6-e6",
        "f4-f2",
        "b4-b3",
        "c4-c6",
        "b3-c3",
        "d5-e5",
        "d1-e1",
        "c6-b6",
        "e1-e3xd3",
        "d4-d3",
        "a4-b4",
        "f2-f3xe3",
        "g4-e4xe5",
        "d3-d5",
        "b4-b5",
        "f3-f4xe4",
        "e6-e5",
        "d5-d4",
        "b5-b4",
        "b6-f6xf5",
        "b4-c4",
        "f4-f5",
        "resigned"
    ],
    "WhoWon": "White"
}