{
    "WhiteSidePlayerName": "crust",
    "BlackSidePlayerName": "tonythebook",
    "AageGameTypeKey": 26,
    "AageGameTypeName": "Sea battle tafl 11x11",
    "WhoMovedFirst": "black",
    "BlackPiecesCaptured": 3,
    "WhitePiecesCaptured": 1,
    "Moves": [
        "b6-b3",
        "e6-e5",
        "f2-c2",
        "f5-j5",
        "j6-j9",
        "i6-i1",
        "f10-i10",
        "g6-g2",
        "i10-i5xj5",
        "f4-i4",
        "k4-k1",
        "f6-g6",
        "g11-g10",
        "g6-g3",
        "j9-j3",
        "g3-i3",
        "k5-k2",
        "h6-i6xi5",
        "k8-i8",
        "i4-k4",
        "g10-g3xg2",
        "i3-i5",
        "j3-j5",
        "i5-i2",
        "k2-j2",
        "i1-j1",
        "h1-i1xj1",
        "i2-h2",
        "resigned"
    ],
    "WhoWon": "White"
}