{
    "WhiteSidePlayerName": "Holidayinnes",
    "BlackSidePlayerName": "Xerxes",
    "AageGameTypeKey": 162,
    "AageGameTypeName": "Dald&oslash;s 3x12",
    "WhoMovedFirst": "black",
    "BlackPiecesCaptured": 0,
    "WhitePiecesCaptured": 0,
    "Moves": [
        "nox",
        "a1-b1",
        "nox",
        "a3-a2",
        "nox",
        "b10-c12xc12",
        "nox",
        "c12-c11xc11",
        "nox",
        "c9-c7xc7",
        "nox",
        "c7-c4xc4",
        "c1-b3",
        "a2-b3xb3",
        "c2-b3xb3",
        "c10-c6xc6",
        "b3-b9",
        "c4-c3xc3",
        "c8-c7",
        "b5-b12xb12"
    ],
    "WhoWon": "White"
}