{
    "WhiteSidePlayerName": "meersburg",
    "BlackSidePlayerName": "mmagari",
    "AageGameTypeKey": 16,
    "AageGameTypeName": "Copenhagen Hnefatafl 11x11",
    "WhoMovedFirst": "black",
    "BlackPiecesCaptured": 2,
    "WhitePiecesCaptured": 4,
    "Moves": [
        "k8-i8",
        "e5-b5",
        "b6-b9",
        "f4-c4",
        "f2-b2",
        "f5-c5",
        "f1-f3",
        "e6-e3",
        "d1-d3xe3",
        "e7-e3",
        "e1-c1",
        "c4-c3xd3",
        "a4-a3",
        "g5-g3xf3",
        "j6-j2",
        "g3-k3",
        "h1-i1",
        "h6-h1",
        "g1-g3",
        "f6-f2",
        "g3-i3",
        "g6-g2",
        "h11-h3",
        "d6-d1",
        "d11-d3",
        "f7-f3",
        "a3-b3xc3",
        "c5-c3xd3",
        "b2-e2",
        "d1-e1xe2",
        "b3-b2",
        "e3-e2",
        "resigned"
    ],
    "WhoWon": "White"
}