{
    "WhiteSidePlayerName": "Polychoron",
    "BlackSidePlayerName": "RedPython",
    "AageGameTypeKey": 15,
    "AageGameTypeName": "Old Hnefatafl 11x11",
    "WhoMovedFirst": "black",
    "BlackPiecesCaptured": 12,
    "WhitePiecesCaptured": 4,
    "Moves": [
        "j6-j10",
        "h6-j6",
        "f2-j2",
        "f4-j4",
        "a4-i4xj4",
        "f5-f4",
        "i4-i6xj6",
        "g5-i5",
        "k4-i4xi5",
        "e5-i5",
        "b6-b2",
        "g7-i7xi6",
        "k6-i6xi5",
        "f8-i8",
        "h11-i11",
        "d6-c6",
        "f10-b10",
        "i8-i10",
        "k8-i8xi7",
        "e7-c7",
        "h1-h10xi10",
        "c7-c11",
        "b10-b11xc11",
        "f4-c4",
        "b11-b10",
        "f7-c7",
        "d11-c11",
        "c4-c1",
        "b2-b1xc1",
        "c6-c1xb1",
        "b10-b1xc1",
        "c7-c1xb1",
        "j2-b2",
        "e6-c6",
        "h10-b10",
        "f6-d6",
        "i6-h6xg6",
        "c6-b6",
        "c11-c6xb6",
        "d6-d3",
        "j10-j2",
        "d3-a3",
        "b2-a2",
        "c1-c2",
        "b10-b2",
        "a3-k3",
        "j2-k2",
        "k3-i3",
        "k2-j2",
        "i3-a3xa2",
        "b2-a2",
        "c2-b2",
        "j2-c2xb2",
        "a3-k3",
        "c2-k2",
        "k3-j3",
        "g1-j1",
        "j3-j9",
        "i11-j11",
        "j9-k9",
        "i8-i10",
        "k9-k11"
    ],
    "WhoWon": "White"
}