{
    "WhiteSidePlayerName": "Harry64",
    "BlackSidePlayerName": "Chillin",
    "AageGameTypeKey": 16,
    "AageGameTypeName": "Copenhagen Hnefatafl 11x11",
    "WhoMovedFirst": "black",
    "BlackPiecesCaptured": 2,
    "WhitePiecesCaptured": 1,
    "Moves": [
        "h1-h3",
        "f8-c8",
        "f10-c10",
        "d6-d3",
        "a4-c4",
        "f7-f9",
        "h11-h9",
        "f9-a9",
        "f11-f9",
        "g7-g9",
        "e11-e9",
        "c8-i8",
        "h9-h10",
        "g9-j9",
        "g11-i11",
        "g6-g11",
        "h10-j10",
        "i8-i1",
        "j6-j8xj9",
        "h6-j6",
        "k4-j4",
        "f6-i6",
        "h3-i3",
        "g5-g2",
        "i3-g3xg2",
        "i6-i2",
        "j4-j2",
        "i2-i3",
        "g1-h1",
        "f4-k4",
        "f2-i2",
        "i3-k3",
        "j2-k2",
        "k3-i3xi2",
        "k2-j2",
        "i3-j3",
        "resigned"
    ],
    "WhoWon": "White"
}