{
    "WhiteSidePlayerName": "sea slug",
    "BlackSidePlayerName": "Hjuke",
    "AageGameTypeKey": 10,
    "AageGameTypeName": "Skalk Hnefatafl 9x9 (ExpoMedia)",
    "WhoMovedFirst": "black",
    "BlackPiecesCaptured": 0,
    "WhitePiecesCaptured": 0,
    "Moves": [
        "h5h7",
        "e3b3",
        "a4a3",
        "e4a4",
        "e2b2",
        "a4b4",
        "a6b6",
        "e7c7",
        "d1c1",
        "c7a7",
        "a5a6",
        "c5c8",
        "d9c9",
        "c8b8",
        "e9d9",
        "g5h5",
        "f1h1",
        "f5f8",
        "d9d8",
        "f8h8",
        "f9h9",
        "e5g5",
        "e1g1",
        "g5g9",
        "h7h9",
        "g9e9",
        "h9f9",
        "e6e7",
        "c9d9"
    ],
    "WhoWon": "Black"
}