{
    "WhiteSidePlayerName": "Beyn",
    "BlackSidePlayerName": "Jrton80",
    "AageGameTypeKey": 76,
    "AageGameTypeName": "Historical Hnefatafl 11x11 (Welsh Tawlbwrdd)",
    "WhoMovedFirst": "black",
    "BlackPiecesCaptured": 7,
    "WhitePiecesCaptured": 0,
    "Moves": [
        "e2-c2",
        "f8-c8",
        "b7-c7",
        "d6-d9",
        "e10-d10",
        "e7-e9",
        "g10-g9",
        "e5-e3",
        "g2-g3",
        "h6-h2",
        "g1-g2",
        "f4-i4",
        "j5-i5",
        "e6-e4",
        "e1-d1",
        "e3-e2",
        "f1-f2",
        "f6-d6",
        "k7-k8",
        "i4-i3",
        "d1-d2xe2",
        "e4-e3",
        "d2-d3xe3",
        "h2-j2",
        "i6-h6xg6",
        "d6-e6",
        "f3-e3",
        "f5-d5",
        "f2-f4",
        "c8-c10",
        "b5-b10xc10",
        "j2-j5",
        "h6-h5",
        "e6-e8",
        "b10-b8",
        "e8-i8",
        "d10-i10",
        "d9-c9",
        "f9-f8xf7",
        "g7-f7",
        "f8-f9",
        "i8-d8",
        "i10-d10",
        "c9-c10",
        "e11-e10",
        "d8-h8",
        "g9-h9",
        "h8-i8",
        "g11-i11",
        "i8-g8",
        "f9-g9",
        "g8-e8",
        "f11-f9",
        "j5-j6",
        "k5-j5xj6",
        "e8-d8",
        "c7-c8",
        "d8-d7",
        "c6-d6",
        "d7-e7",
        "d3-d4xd5",
        "e9-c9",
        "a7-d7",
        "e7-e5",
        "a5-d5",
        "e5-e8",
        "k8-g8",
        "resigned"
    ],
    "WhoWon": "Black"
}