{
    "WhiteSidePlayerName": "holidayinnes",
    "BlackSidePlayerName": "rosk",
    "AageGameTypeKey": 148,
    "AageGameTypeName": "Hex 11x11",
    "WhoMovedFirst": "black",
    "BlackPiecesCaptured": null,
    "WhitePiecesCaptured": null,
    "Moves": [
        "b6",
        "f6",
        "d7",
        "g8",
        "h10",
        "g9",
        "g10",
        "i10",
        "h9",
        "h8",
        "i9",
        "f10",
        "f9",
        "c7",
        "e9",
        "d9",
        "c6",
        "j9",
        "j10",
        "d8",
        "e8",
        "k10",
        "k11",
        "a6",
        "a5"
    ],
    "WhoWon": "Black"
}