{
    "WhiteSidePlayerName": "Paul7",
    "BlackSidePlayerName": "Draganov",
    "AageGameTypeKey": 17,
    "AageGameTypeName": "Tawlbwrdd T diamond 11x11",
    "WhoMovedFirst": "black",
    "BlackPiecesCaptured": 5,
    "WhitePiecesCaptured": 1,
    "Moves": [
        "h1-h3",
        "d6-d9",
        "h11-h9",
        "e7-b7",
        "a5-b5",
        "f4-d4",
        "a4-c4",
        "e6-e8",
        "a8-b8xb7",
        "f6-c6",
        "f10-c10",
        "e5-e3",
        "k4-e4xd4",
        "e3-d3",
        "f2-f4xf5",
        "g6-d6",
        "d1-d2",
        "d9-b9",
        "a7-b7",
        "d3-a3",
        "b5-c5",
        "f7-c7",
        "d11-d7xc7",
        "c6-c7",
        "b6-c6",
        "e8-c8",
        "e4-e7",
        "a3-b3",
        "d7-d8xc8",
        "c7-c8",
        "c10-c9",
        "f8-e8xd8",
        "c6-c7"
    ],
    "WhoWon": "Black"
}