{
    "WhiteSidePlayerName": "Wesley Alves",
    "BlackSidePlayerName": "unhandyandy",
    "AageGameTypeKey": 129,
    "AageGameTypeName": "Historical Hnefatafl 7x7 (Irish Brandubh 2)",
    "WhoMovedFirst": "black",
    "BlackPiecesCaptured": 3,
    "WhitePiecesCaptured": 0,
    "Moves": [
        "d2-e2",
        "c4-c2",
        "b4-b3",
        "d4-b4",
        "d6-c6",
        "d5-c5",
        "b3-b2",
        "d3-a3",
        "b2-a2xa3",
        "e4-c4",
        "a2-b2",
        "c5-a5",
        "c6-a6xa5",
        "b4-b5",
        "a6-b6",
        "b5-c5",
        "e2-d2xc2",
        "c4-e4",
        "f4-f5",
        "e4-e6",
        "b6-c6",
        "c5-c2",
        "d2-e2",
        "c2-c3",
        "b2-b3",
        "c3-d3",
        "e2-e3",
        "d3-d5",
        "f5-e5",
        "resigned"
    ],
    "WhoWon": "Black"
}