{
    "WhiteSidePlayerName": "Wotan",
    "BlackSidePlayerName": "tonythebook",
    "AageGameTypeKey": 16,
    "AageGameTypeName": "Copenhagen Hnefatafl 11x11",
    "WhoMovedFirst": "black",
    "BlackPiecesCaptured": 4,
    "WhitePiecesCaptured": 4,
    "Moves": [
        "h1-h3",
        "g5-g2",
        "h3-g3xg2",
        "h6-h3",
        "f2-f3",
        "g6-g4",
        "j6-h6",
        "f6-g6",
        "k4-k3",
        "g7-i7",
        "g11-g9",
        "i7-i6xh6",
        "k6-j6",
        "h3-h9",
        "g1-h1",
        "f8-f9xg9",
        "a8-f8xf9xf7",
        "g6-g10",
        "j6-j10",
        "h9-k9",
        "h11-h10",
        "g10-g11",
        "h10-h11",
        "i6-i11xh11",
        "k5-g5xg4",
        "g11-h11",
        "g5-j5",
        "i11-i10",
        "j10-j11",
        "i10-i11xj11",
        "h1-h10",
        "i11-i10",
        "j5-j11",
        "timeout"
    ],
    "WhoWon": "Black"
}