{
    "WhiteSidePlayerName": "Thanir",
    "BlackSidePlayerName": "Ragnvald",
    "AageGameTypeKey": 16,
    "AageGameTypeName": "Copenhagen Hnefatafl 11x11",
    "WhoMovedFirst": "black",
    "BlackPiecesCaptured": 2,
    "WhitePiecesCaptured": 5,
    "Moves": [
        "d1-d3",
        "f4-c4",
        "d11-c11",
        "e5-b5",
        "f2-f4",
        "g5-g3",
        "f4-f3",
        "e6-e3xf3",
        "f1-f3xe3",
        "e7-e3xf3",
        "d3-b3",
        "f5-j5",
        "k4-f4",
        "f6-f5",
        "h1-h5",
        "g3-f3xf4",
        "g1-g3",
        "c4-h4xh5",
        "k7-i7",
        "h4-h3xg3",
        "i7-i5xj5",
        "f3-f1",
        "e1-c1",
        "f5-f2",
        "resigned"
    ],
    "WhoWon": "White"
}