{
    "WhiteSidePlayerName": "the fifth seal",
    "BlackSidePlayerName": "altti",
    "AageGameTypeKey": 16,
    "AageGameTypeName": "Copenhagen Hnefatafl 11x11",
    "WhoMovedFirst": "black",
    "BlackPiecesCaptured": 2,
    "WhitePiecesCaptured": 4,
    "Moves": [
        "k8-i8",
        "g7-j7",
        "k5-j5",
        "f8-c8",
        "e11-e9",
        "d6-d9",
        "f10-f9",
        "j7-j10",
        "h11-h10",
        "g6-g8",
        "a4-c4",
        "h6-h8",
        "i8-i6",
        "f6-h6",
        "k4-h4",
        "g5-i5",
        "k7-i7",
        "h8-k8",
        "g11-j11",
        "j10-j9",
        "f11-i11",
        "i5-i3",
        "f2-i2",
        "h6-h9",
        "j6-j7",
        "g8-g11",
        "h10-j10",
        "h9-h10",
        "b6-b10",
        "c8-c11",
        "b10-f10",
        "h10-i10",
        "i7-i9",
        "k8-i8xi9xj10xi9",
        "j7-j8xj9",
        "g11-e11xd11",
        "g1-g10",
        "i8-e8",
        "h4-h10",
        "i10-i9",
        "j10-j9",
        "e11-e10xe9",
        "h1-h9",
        "f5-i5",
        "i6-i7",
        "i9-i8",
        "h9-h5xi5",
        "e6-i6xi7",
        "h5-h4",
        "i8-g8",
        "d1-d3",
        "g8-g1",
        "h4-h1",
        "g1-g4",
        "j5-j4",
        "i3-k3",
        "j4-i4",
        "g4-g3",
        "i4-i3",
        "g3-h3",
        "j8-j3",
        "f7-k7",
        "k6-k5",
        "f4-k4",
        "k5-h5",
        "h3-h4",
        "h10-h6",
        "h4-d4",
        "a6-c6",
        "d4-d8",
        "a8-c8",
        "d9-b9",
        "resigned"
    ],
    "WhoWon": "White"
}