{
    "WhiteSidePlayerName": "mmagari",
    "BlackSidePlayerName": "holidayinnes",
    "AageGameTypeKey": 51,
    "AageGameTypeName": "Historical Hnefatafl 7x7 (Irish Brandubh 1)",
    "WhoMovedFirst": "black",
    "BlackPiecesCaptured": 2,
    "WhitePiecesCaptured": 1,
    "Moves": [
        "d2-e2",
        "c4-c2",
        "d6-c6",
        "c2-b2",
        "d1-b1",
        "d3-g3",
        "e2-d2",
        "d5-g5xg4",
        "f4-g4",
        "e4-e2",
        "b4-b3xb2",
        "d4-d3",
        "c6-g6xg5",
        "d3-f3",
        "b1-f1",
        "timeout"
    ],
    "WhoWon": "Black"
}