{
    "WhiteSidePlayerName": "Crust",
    "BlackSidePlayerName": "Vonraider",
    "AageGameTypeKey": 31,
    "AageGameTypeName": "Simple Tafl 11x11",
    "WhoMovedFirst": "black",
    "BlackPiecesCaptured": 1,
    "WhitePiecesCaptured": 3,
    "Moves": [
        "g2-i2",
        "e6-e4",
        "e10-d10",
        "f6-e6",
        "b7-b8",
        "f9-a9",
        "f10-f9",
        "c6-c11",
        "b8-a8",
        "e4-a4",
        "d10-a10xa9",
        "e6-e9",
        "b6-b9",
        "g6-g9xf9",
        "j7-j9",
        "e9-c9",
        "a7-c7",
        "c11-b11",
        "e11-c11",
        "d6-d11xc11",
        "a10-c10",
        "d11-c11xc10",
        "g10-c10",
        "c9-d9",
        "a6-d6",
        "d9-d11"
    ],
    "WhoWon": "White"
}