{
    "WhiteSidePlayerName": "Xerxes",
    "BlackSidePlayerName": "Docbullen",
    "AageGameTypeKey": 33,
    "AageGameTypeName": "Historical Hnefatafl 13x13",
    "WhoMovedFirst": "black",
    "BlackPiecesCaptured": 11,
    "WhitePiecesCaptured": 2,
    "Moves": [
        "h2-j2",
        "g8-g9",
        "h1-h3",
        "f7-e7",
        "i1-i4",
        "h6-i6",
        "j2-j5",
        "h7-h4",
        "l6-j6",
        "h8-h10",
        "m9-k9",
        "f6-f3",
        "l8-j8xj7",
        "g7-j7",
        "k9-j9",
        "h10-l10",
        "m8-l8",
        "g9-h9",
        "m7-m9",
        "l10-l9",
        "j9-k9xl9",
        "e7-e8",
        "i13-i10",
        "e9-b9",
        "h12-h10",
        "e8-e12",
        "e1-e3xf3",
        "j7-f7",
        "g11-e11xe12",
        "d7-d11",
        "f12-f10xg10",
        "f7-f4",
        "c7-c4",
        "e5-b5",
        "a7-b7",
        "g6-d6",
        "g13-g5xg4",
        "f4-g4",
        "f2-f5",
        "d6-h6",
        "j8-h8xh9",
        "d11-d3",
        "f10-g10",
        "d3-c3",
        "g5-h5xi5xh4",
        "g4-g7",
        "b7-c7",
        "b5-c5xc4",
        "l8-i8xi9",
        "g7-g6",
        "e3-e6",
        "g6-g5",
        "i4-g4",
        "g5-g8",
        "g10-g9",
        "g8-g7",
        "c7-d7",
        "g7-f7",
        "e11-e7",
        "f8-e8",
        "f13-f10",
        "e8-g8",
        "f10-f8xg8",
        "b9-f9xf8",
        "b8-f8",
        "resigned"
    ],
    "WhoWon": "Black"
}