{
    "WhiteSidePlayerName": "Ssmm155",
    "BlackSidePlayerName": "mrm",
    "AageGameTypeKey": 26,
    "AageGameTypeName": "Sea battle tafl 11x11",
    "WhoMovedFirst": "black",
    "BlackPiecesCaptured": 4,
    "WhitePiecesCaptured": 5,
    "Moves": [
        "a7-c7",
        "f8-c8xc7",
        "k8-f8xf9",
        "d6-d5",
        "d11-d6xc6",
        "c8-c6xd6",
        "e11-e7",
        "d5-d7xe7",
        "d1-d6xc6",
        "f5-d5xd6",
        "b6-d6",
        "g6-g8",
        "a4-d4xd5",
        "f6-g6",
        "k5-g5",
        "g6-g7",
        "h11-h7",
        "g8-h8xh7",
        "k7-h7",
        "g7-g9",
        "g5-g8",
        "g9-k9"
    ],
    "WhoWon": "White"
}