{
    "WhiteSidePlayerName": "remi",
    "BlackSidePlayerName": "Siegfried",
    "AageGameTypeKey": 15,
    "AageGameTypeName": "Old Hnefatafl 11x11",
    "WhoMovedFirst": "black",
    "BlackPiecesCaptured": 0,
    "WhitePiecesCaptured": 0,
    "Moves": [
        "d11d9",
        "g5h5",
        "h1h3",
        "h6h10",
        "d9h9",
        "e7e9",
        "e11e10",
        "e5e4",
        "a8d8",
        "f7d7",
        "d8d9",
        "d7c7",
        "f10f9",
        "c7b7",
        "a5c5",
        "b7b9",
        "a7c7",
        "e6e9",
        "c7f7",
        "e4e7",
        "f9f7",
        "b9c9",
        "k7h7",
        "e9f9",
        "k8f8",
        "g6h6",
        "f11f10",
        "f6g6",
        "g11g7",
        "f4j4",
        "g1g4",
        "h5i5",
        "f2f4",
        "resigned"
    ],
    "WhoWon": "Black"
}