{
    "WhiteSidePlayerName": "the fifth seal",
    "BlackSidePlayerName": "Leafbeard",
    "AageGameTypeKey": 16,
    "AageGameTypeName": "Copenhagen Hnefatafl 11x11",
    "WhoMovedFirst": "black",
    "BlackPiecesCaptured": 4,
    "WhitePiecesCaptured": 7,
    "Moves": [
        "h1-h4",
        "g5-i5",
        "k4-i4",
        "g7-g10",
        "h11-h10xg10",
        "g6-g3",
        "g11-g9",
        "g3-i3xi4",
        "g1-g6",
        "f5-g5",
        "h4-g4xg5",
        "h6-h4xg4",
        "j6-h6",
        "f6-f5",
        "f2-g2",
        "f4-f2",
        "e1-e2xf2",
        "f5-f2",
        "a4-f4",
        "h4-h2xg2",
        "g6-g2",
        "d6-d2xe2",
        "b6-b2",
        "f2-f3",
        "a5-a3",
        "f7-f5xf4",
        "d11-d4",
        "d2-f2xg2",
        "g9-g4",
        "f3-g3",
        "f1-g1",
        "f5-g5xg4",
        "a6-d6xe6",
        "i3-i1",
        "k5-k3",
        "g3-j3",
        "a3-i3",
        "j3-j11",
        "f11-i11",
        "j11-k11"
    ],
    "WhoWon": "White"
}