{
    "WhiteSidePlayerName": "Khan asparukh",
    "BlackSidePlayerName": "Hagbard",
    "AageGameTypeKey": 76,
    "AageGameTypeName": "Historical Hnefatafl 11x11 (Welsh Tawlbwrdd)",
    "WhoMovedFirst": "black",
    "BlackPiecesCaptured": 5,
    "WhitePiecesCaptured": 6,
    "Moves": [
        "g11-h11",
        "e7-e9",
        "g10-g9",
        "e5-e3",
        "g2-g3",
        "f7-c7",
        "e11-c11",
        "f5-c5xc6",
        "a5-a3",
        "d6-b6",
        "b5-b4",
        "f8-b8xb7",
        "a3-d3xe3",
        "f6-f8",
        "h11-h8",
        "f8-d8",
        "f11-d11",
        "e9-a9",
        "d11-d9",
        "g7-d7",
        "e10-a10",
        "e6-e9",
        "d9-d10",
        "c7-c10",
        "d10-d11",
        "d8-d9",
        "f9-f5xf4",
        "b8-b11",
        "a10-a11xb11",
        "d9-b9",
        "c11-b11",
        "c10-a10",
        "h8-a8",
        "c5-e5xf5",
        "e1-c1",
        "a10-g10",
        "b11-b10",
        "b9-c9",
        "b10-c10",
        "c9-c8",
        "g9-g8",
        "g6-g7",
        "g8-f8",
        "g7-g8",
        "c1-c6xb6",
        "c8-e8xf8",
        "a11-a10xa9",
        "e8-f8",
        "d11-f11",
        "e9-e11",
        "i6-i9",
        "g8-g9",
        "i9-i8",
        "g10-g11xf11",
        "c10-f10",
        "g11-g10",
        "k7-k11",
        "e5-e10xf10",
        "resigned"
    ],
    "WhoWon": "White"
}