{
    "WhiteSidePlayerName": "Agmundr",
    "BlackSidePlayerName": "crust",
    "AageGameTypeKey": 76,
    "AageGameTypeName": "Historical Hnefatafl 11x11 (Welsh Tawlbwrdd)",
    "WhoMovedFirst": "black",
    "BlackPiecesCaptured": 10,
    "WhitePiecesCaptured": 0,
    "Moves": [
        "f3-d3",
        "h6-h9",
        "g10-h10",
        "g7-g9",
        "f9-d9",
        "g5-g3",
        "i6-i4",
        "g6-i6",
        "g2-h2",
        "f6-h6",
        "j7-j8",
        "h6-h8",
        "c6-c8",
        "i6-i10",
        "g11-g10",
        "h9-j9",
        "k7-i7",
        "e6-i6",
        "j5-i5xi6",
        "d6-i6",
        "i7-j7",
        "h8-h6",
        "j7-i7xi6",
        "h6-c6",
        "e2-c2",
        "e5-e2",
        "d3-e3xe2",
        "c6-d6",
        "e3-d3",
        "d6-g6",
        "f11-j11",
        "i10-j10",
        "j8-g8xg9",
        "f5-h5",
        "g8-j8",
        "g3-j3",
        "i4-j4",
        "h5-h3",
        "h2-j2xj3",
        "f4-i4",
        "j2-h2",
        "f8-i8",
        "h10-h8xi8",
        "j9-h9",
        "h8-h4xi4xh3",
        "f7-f10",
        "g10-g8",
        "h9-g9",
        "i7-g7",
        "g6-h6",
        "g8-h8",
        "h6-f6",
        "e11-f11",
        "f6-f4",
        "b5-b4",
        "f4-f9",
        "j8-j9xj10",
        "g9-h9",
        "g7-g10xf10",
        "f9-f7",
        "h4-h7",
        "f7-f3",
        "g1-g3",
        "f3-f6",
        "k6-g6",
        "resigned"
    ],
    "WhoWon": "Black"
}