{
    "WhiteSidePlayerName": "Draganov",
    "BlackSidePlayerName": "Alex hnefatafl",
    "AageGameTypeKey": 145,
    "AageGameTypeName": "Tyr 15x15",
    "WhoMovedFirst": "black",
    "BlackPiecesCaptured": 3,
    "WhitePiecesCaptured": 4,
    "Moves": [
        "g4-g2",
        "h11-h12",
        "i12-i14",
        "f9-f12xg12",
        "c13-e13",
        "e8-d8",
        "d9-b9",
        "g6-d6xd7",
        "c3-c5",
        "k8-l8",
        "l7-n7",
        "i10-l10xl9",
        "m13-k13",
        "j9-n9",
        "m10-o10",
        "g10-g14",
        "f13-f14",
        "h9-c9",
        "c10-b10",
        "k11-o11",
        "o8-o9",
        "e11-a11",
        "d12-d9xc9",
        "h8-h11",
        "d15-d11",
        "h11-e11",
        "a8-a10xa11",
        "d8-a8",
        "b10-c10",
        "e11-g11",
        "a15-g15",
        "f7-a7",
        "a12-e12",
        "a7-a6",
        "c6-c7",
        "a6-a7",
        "a4-a6",
        "g14-g12",
        "a10-a9",
        "d6-c6",
        "a1-a5",
        "g8-c8xc7",
        "d1-e1",
        "g11-g7",
        "e1-e3",
        "a7-b7",
        "a5-b5",
        "l8-o8",
        "o4-o7xo8",
        "i8-o8",
        "m3-m5",
        "k5-k2",
        "l1-l2",
        "k2-k1",
        "o1-l1",
        "h5-h4",
        "i4-i1",
        "k1-k11",
        "m9-m13",
        "k11-n11",
        "l15-n15",
        "b7-a7",
        "l2-k2",
        "h7-h9",
        "i1-i3",
        "g7-b7",
        "b5-b6",
        "a8-b8",
        "h1-h3",
        "c8-m8",
        "n15-n13",
        "resigned"
    ],
    "WhoWon": "Black"
}