{
    "WhiteSidePlayerName": "cdafo",
    "BlackSidePlayerName": "Jrton80",
    "AageGameTypeKey": 16,
    "AageGameTypeName": "Copenhagen Hnefatafl 11x11",
    "WhoMovedFirst": "black",
    "BlackPiecesCaptured": 3,
    "WhitePiecesCaptured": 1,
    "Moves": [
        "e1-e3",
        "f8-c8",
        "d1-d3",
        "e7-e10",
        "g11-g9",
        "e6-e9",
        "f10-i10",
        "d6-d9",
        "d11-c11",
        "e10-b10",
        "a8-b8",
        "c8-c10",
        "a7-a9",
        "b10-b9",
        "b6-b7",
        "d9-d11",
        "a6-c6",
        "e9-c9",
        "a5-d5",
        "f6-d6",
        "d3-d4",
        "d6-d10",
        "f11-f8xf7",
        "c10-a10",
        "f8-c8",
        "d10-b10",
        "i10-c10xc9",
        "b10-b11xc11",
        "c10-c11xd11",
        "b11-a11"
    ],
    "WhoWon": "White"
}